{
  "schemaVersion": 1,
  "id": "c2me",
  "version": "${version}",
  "name": "Concurrent Chunk Management Engine",
  "description": "A Fabric mod designed to improve the chunk performance of Minecraft.",
  "authors": [
    "YatopiaMC",
    "ishland"
  ],
  "contact": {
    "website": "https://yatopiamc.org/",
    "repo": "https://github.com/YatopiaMC/C2ME-fabric"
  },
  "license": "MIT",
  "icon": "assets/c2me/icon.png",
  "environment": "*",
  "entrypoints": {
    "main": [
      "org.yatopiamc.c2me.C2MEMod"
    ]
  },
  "accessWidener" : "c2me.accesswidener",
  "mixins": [
    "c2me.mixins.json"
  ],
  "depends": {
    "fabricloader": ">=0.11.1",
    "java": ">=11",
    "minecraft": ">=1.16.4"
  },
  "breaks": {
    "tic_tacs": "*"
  }
}
